easyrepl/__init__.py
easyrepl/repl.py
easyrepl-0.1.5.dist-info/LICENSE
easyrepl-0.1.5.dist-info/METADATA
easyrepl-0.1.5.dist-info/WHEEL
easyrepl-0.1.5.dist-info/RECORD
