Metadata-Version: 2.1
Name: easyrepl
Version: 0.1.5
Summary: A simple python class for creating Read Evaluate Print Line (REPL) interfaces
Home-page: https://github.com/david-andrew/EasyREPL
License: MIT
Author: David Samson
Author-email: david.andrew.engineer@gmail.com
Requires-Python: >=3.7
Classifier: License :: OSI Approved :: MIT License
Classifier: Operating System :: POSIX
Classifier: Programming Language :: Python :: 3
Classifier: Programming Language :: Python :: 3.7
Classifier: Programming Language :: Python :: 3.8
Classifier: Programming Language :: Python :: 3.9
Classifier: Programming Language :: Python :: 3.10
Classifier: Programming Language :: Python :: 3.11
Project-URL: Bug Tracker, https://github.com/david-andrew/EasyREPL/issues
